dagster_celery/__init__.py
dagster_celery/app.py
dagster_celery/cli.py
dagster_celery/config.py
dagster_celery/core_execution_loop.py
dagster_celery/defaults.py
dagster_celery/executor.py
dagster_celery/make_app.py
dagster_celery/tags.py
dagster_celery/tasks.py
dagster_celery/version.py
dagster_celery-1.0.5.dist-info/LICENSE
dagster_celery-1.0.5.dist-info/METADATA
dagster_celery-1.0.5.dist-info/WHEEL
dagster_celery-1.0.5.dist-info/entry_points.txt
dagster_celery-1.0.5.dist-info/top_level.txt
dagster_celery-1.0.5.dist-info/RECORD
