Metadata-Version: 2.1
Name: dagster-celery
Version: 1.0.5
Summary: Package for using Celery as Dagster's execution engine.
Home-page: https://github.com/dagster-io/dagster/tree/master/python_modules/libraries/dagster-celery
Author: Elementl
Author-email: hello@elementl.com
License: Apache-2.0
Platform: UNKNOWN
Classifier: Programming Language :: Python :: 3.7
Classifier: Programming Language :: Python :: 3.8
Classifier: Programming Language :: Python :: 3.9
Classifier: Programming Language :: Python :: 3.10
Classifier: License :: OSI Approved :: Apache Software License
Classifier: Operating System :: OS Independent
License-File: LICENSE
Requires-Dist: dagster (==1.0.5)
Requires-Dist: celery (>=4.3.0)
Requires-Dist: click (<9.0,>=5.0)
Provides-Extra: flower
Requires-Dist: flower ; extra == 'flower'
Provides-Extra: kubernetes
Requires-Dist: kubernetes ; extra == 'kubernetes'
Provides-Extra: redis
Requires-Dist: redis ; extra == 'redis'
Provides-Extra: test
Requires-Dist: docker ; extra == 'test'
